apigateway/__init__.py
apigateway/base.py
apigateway/default.py
apigateway/event.py
apigateway/format.py
apigateway/request.py
apigateway/response.py
apigateway/settings.py
apigateway/startup.py
apigateway/utils.py
apigateway/views.py
flask_turn_apigateway-0.3.0.dist-info/METADATA
flask_turn_apigateway-0.3.0.dist-info/WHEEL
flask_turn_apigateway-0.3.0.dist-info/top_level.txt
flask_turn_apigateway-0.3.0.dist-info/RECORD
